icddl/__init__.py
icddl/main.py
chateda-0.1.0.dist-info/METADATA
chateda-0.1.0.dist-info/WHEEL
chateda-0.1.0.dist-info/entry_points.txt
chateda-0.1.0.dist-info/top_level.txt
chateda-0.1.0.dist-info/RECORD
