Metadata-Version: 2.1
Name: chateda
Version: 0.1.0
Summary: integrated circuit conference information
Author: ChatEDA
License: MIT
Requires-Dist: tabulate (>=0.8.10)
Requires-Dist: requests (>=2.32.3)
Requires-Dist: termcolor (>=2.4.0)
Requires-Dist: arxiv (>=2.1.3)
Requires-Dist: pyyaml (>=6.0)
